itchat/__init__.py
itchat/config.py
itchat/content.py
itchat/core.py
itchat/log.py
itchat/returnvalues.py
itchat/utils.py
itchat/async_components/__init__.py
itchat/async_components/contact.py
itchat/async_components/hotreload.py
itchat/async_components/login.py
itchat/async_components/messages.py
itchat/async_components/register.py
itchat/components/__init__.py
itchat/components/contact.py
itchat/components/hotreload.py
itchat/components/login.py
itchat/components/messages.py
itchat/components/register.py
itchat/storage/__init__.py
itchat/storage/messagequeue.py
itchat/storage/templates.py
itchat_on-1.5.0.dev0.dist-info/LICENSE
itchat_on-1.5.0.dev0.dist-info/METADATA
itchat_on-1.5.0.dev0.dist-info/WHEEL
itchat_on-1.5.0.dev0.dist-info/top_level.txt
itchat_on-1.5.0.dev0.dist-info/RECORD
